[
{"nombre_colonia":"1 De Mayo","centro":[-103.335,20.628],"riesgo":45},
{"nombre_colonia":"18 De Marzo","centro":[-103.342,20.635],"riesgo":96},
{"nombre_colonia":"20 De Noviembre","centro":[-103.328,20.665],"riesgo":64},
{"nombre_colonia":"5 De Mayo","centro":[-103.345,20.695],"riesgo":63},
{"nombre_colonia":"8 De Julio","centro":[-103.355,20.642],"riesgo":57},
{"nombre_colonia":"Aaron Joaquin","centro":[-103.285,20.682],"riesgo":64},
{"nombre_colonia":"Agraria","centro":[-103.312,20.678],"riesgo":39},
{"nombre_colonia":"Agua Escondida","centro":[-103.31,20.715],"riesgo":26},
{"nombre_colonia":"Agustin Yañez","centro":[-103.368,20.662],"riesgo":68},
{"nombre_colonia":"Alameda","centro":[-103.332,20.676],"riesgo":83},
{"nombre_colonia":"Alamedas De Zalatitan","centro":[-103.262,20.658],"riesgo":32},
{"nombre_colonia":"Alamo Industrial","centro":[-103.325,20.618],"riesgo":92},
{"nombre_colonia":"Alcalde Barranquitas","centro":[-103.348,20.69],"riesgo":54},
{"nombre_colonia":"Aldama Tetlan","centro":[-103.285,20.662],"riesgo":85},
{"nombre_colonia":"Altamira","centro":[-103.375,20.705],"riesgo":85},
{"nombre_colonia":"Altos Norte","centro":[-103.335,20.722],"riesgo":14},
{"nombre_colonia":"Analco","centro":[-103.3381,20.6689],"riesgo":86},
{"nombre_colonia":"Arandas","centro":[-103.275,20.695],"riesgo":86},
{"nombre_colonia":"Arcinas Las Flores","centro":[-103.31,20.685],"riesgo":63},
{"nombre_colonia":"Artesanos","centro":[-103.351,20.682],"riesgo":53},
{"nombre_colonia":"Atemajac Del Valle","centro":[-103.352,20.718],"riesgo":42},
{"nombre_colonia":"Atlas","centro":[-103.322,20.648],"riesgo":64},
{"nombre_colonia":"Autocinema","centro":[-103.34,20.712],"riesgo":13},
{"nombre_colonia":"Ayuntamiento","centro":[-103.355,20.692],"riesgo":45},
{"nombre_colonia":"Balcones De La Joya","centro":[-103.305,20.732],"riesgo":72},
{"nombre_colonia":"Balcones De Oblatos","centro":[-103.285,20.705],"riesgo":62},
{"nombre_colonia":"Balcones De Santa Maria","centro":[-103.345,20.605],"riesgo":59},
{"nombre_colonia":"Balcones Del Cuatro","centro":[-103.365,20.608],"riesgo":34},
{"nombre_colonia":"Balcones Y/O Prados De Huentitan","centro":[-103.315,20.725],"riesgo":53},
{"nombre_colonia":"Barranca De Oblatos","centro":[-103.275,20.728],"riesgo":53},
{"nombre_colonia":"Beatriz Hernandez","centro":[-103.292,20.691],"riesgo":70},
{"nombre_colonia":"Belisario Dominguez","centro":[-103.325,20.695],"riesgo":59},
{"nombre_colonia":"Benito Juarez","centro":[-103.282,20.698],"riesgo":56},
{"nombre_colonia":"Blanco Y Cuellar","centro":[-103.318,20.682],"riesgo":28},
{"nombre_colonia":"Bosques Del Boulevard","centro":[-103.358,20.638],"riesgo":61},
{"nombre_colonia":"Brisas Del Nilo","centro":[-103.302,20.645],"riesgo":49},
{"nombre_colonia":"Buenos Aires","centro":[-103.352,20.595],"riesgo":86},
{"nombre_colonia":"Cantarranas","centro":[-103.295,20.678],"riesgo":64},
{"nombre_colonia":"Capilla De Jesus","centro":[-103.358,20.682],"riesgo":83},
{"nombre_colonia":"Centro","centro":[-103.3467,20.6767],"riesgo":19},
{"nombre_colonia":"Centro Barranquitas","centro":[-103.345,20.688],"riesgo":65},
{"nombre_colonia":"Circunvalacion Belisario","centro":[-103.325,20.705],"riesgo":14},
{"nombre_colonia":"Circunvalacion Oblatos","centro":[-103.315,20.698],"riesgo":34},
{"nombre_colonia":"Colinas De Huentitan","centro":[-103.315,20.732],"riesgo":20},
{"nombre_colonia":"Colinas De La Normal","centro":[-103.351,20.698],"riesgo":59},
{"nombre_colonia":"Colon","centro":[-103.365,20.632],"riesgo":44},
{"nombre_colonia":"Colon Industrial","centro":[-103.372,20.642],"riesgo":13},
{"nombre_colonia":"Comercial Abastos","centro":[-103.375,20.658],"riesgo":69},
{"nombre_colonia":"Correccional","centro":[-103.315,20.665],"riesgo":53},
{"nombre_colonia":"Cuauhtemoc","centro":[-103.285,20.692],"riesgo":87},
{"nombre_colonia":"Cumbres Del Nilo","centro":[-103.295,20.648],"riesgo":90},
{"nombre_colonia":"De La Presa","centro":[-103.325,20.725],"riesgo":64},
{"nombre_colonia":"Del Barro","centro":[-103.325,20.685],"riesgo":61},
{"nombre_colonia":"Del Bosque","centro":[-103.385,20.672],"riesgo":60},
{"nombre_colonia":"Del Fresno","centro":[-103.362,20.658],"riesgo":60},
{"nombre_colonia":"Del Periodista","centro":[-103.355,20.702],"riesgo":49},
{"nombre_colonia":"Del Sol","centro":[-103.398,20.652],"riesgo":79},
{"nombre_colonia":"Del Sur","centro":[-103.368,20.625],"riesgo":59},
{"nombre_colonia":"Division Del Norte","centro":[-103.332,20.718],"riesgo":68},
{"nombre_colonia":"Doctores","centro":[-103.338,20.692],"riesgo":85},
{"nombre_colonia":"Dr Valentin Gomez Farias","centro":[-103.305,20.668],"riesgo":65},
{"nombre_colonia":"Echeverria","centro":[-103.375,20.628],"riesgo":47},
{"nombre_colonia":"El Alamo","centro":[-103.322,20.625],"riesgo":28},
{"nombre_colonia":"El Batan","centro":[-103.345,20.725],"riesgo":18},
{"nombre_colonia":"El Bethel","centro":[-103.265,20.695],"riesgo":30},
{"nombre_colonia":"El Carmen","centro":[-103.305,20.688],"riesgo":15},
{"nombre_colonia":"El Dean","centro":[-103.345,20.645],"riesgo":49},
{"nombre_colonia":"El Jaguey","centro":[-103.295,20.702],"riesgo":93},
{"nombre_colonia":"El Manantial","centro":[-103.342,20.608],"riesgo":83},
{"nombre_colonia":"El Molino","centro":[-103.255,20.698],"riesgo":38},
{"nombre_colonia":"El Pinal","centro":[-103.288,20.718],"riesgo":43},
{"nombre_colonia":"El Rastro","centro":[-103.335,20.652],"riesgo":61},
{"nombre_colonia":"El Retiro","centro":[-103.338,20.688],"riesgo":52},
{"nombre_colonia":"El Rocio","centro":[-103.285,20.685],"riesgo":33},
{"nombre_colonia":"El Rosario","centro":[-103.325,20.658],"riesgo":83},
{"nombre_colonia":"El Sauz","centro":[-103.392,20.622],"riesgo":66},
{"nombre_colonia":"El Verde (Planetario)","centro":[-103.322,20.715],"riesgo":41},
{"nombre_colonia":"El Zalate","centro":[-103.265,20.668],"riesgo":59},
{"nombre_colonia":"Electricistas","centro":[-103.332,20.638],"riesgo":48},
{"nombre_colonia":"Esperanza","centro":[-103.308,20.695],"riesgo":33},
{"nombre_colonia":"Fabrica De Atemajac","centro":[-103.355,20.722],"riesgo":59},
{"nombre_colonia":"Federalismo","centro":[-103.352,20.702],"riesgo":73},
{"nombre_colonia":"Ferrocarril","centro":[-103.342,20.658],"riesgo":56},
{"nombre_colonia":"Fidel Velazquez","centro":[-103.332,20.712],"riesgo":52},
{"nombre_colonia":"Flamingo","centro":[-103.365,20.648],"riesgo":58},
{"nombre_colonia":"Fovissste Estadio","centro":[-103.325,20.712],"riesgo":34},
{"nombre_colonia":"Fovissste Miravalle","centro":[-103.342,20.615],"riesgo":76},
{"nombre_colonia":"Francisco Villa","centro":[-103.295,20.698],"riesgo":64},
{"nombre_colonia":"Guadalajara Oriente","centro":[-103.305,20.678],"riesgo":91},
{"nombre_colonia":"Guadalupana","centro":[-103.338,20.718],"riesgo":31},
{"nombre_colonia":"Heliodoro Hernandez Loza","centro":[-103.262,20.715],"riesgo":74},
{"nombre_colonia":"Hermosa Provincia","centro":[-103.285,20.672],"riesgo":91},
{"nombre_colonia":"Hernandez Romo","centro":[-103.318,20.658],"riesgo":62},
{"nombre_colonia":"Higuerillas","centro":[-103.348,20.635],"riesgo":21},
{"nombre_colonia":"Hormiguero","centro":[-103.328,20.695],"riesgo":13},
{"nombre_colonia":"Huentitan El Alto","centro":[-103.305,20.738],"riesgo":70},
{"nombre_colonia":"Huentitan El Bajo","centro":[-103.325,20.732],"riesgo":36},
{"nombre_colonia":"Huerta Baeza","centro":[-103.335,20.642],"riesgo":78},
{"nombre_colonia":"Independencia","centro":[-103.335,20.708],"riesgo":96},
{"nombre_colonia":"Independencia Oriente","centro":[-103.315,20.688],"riesgo":93},
{"nombre_colonia":"Infonavit Estadio","centro":[-103.322,20.705],"riesgo":69},
{"nombre_colonia":"Infonavit Independencia","centro":[-103.325,20.708],"riesgo":27},
{"nombre_colonia":"Insurgentes","centro":[-103.275,20.655],"riesgo":46},
{"nombre_colonia":"Jalisco I Secc","centro":[-103.255,20.698],"riesgo":21},
{"nombre_colonia":"Jalisco Ii Secc","centro":[-103.252,20.702],"riesgo":59},
{"nombre_colonia":"Jardines Alcalde","centro":[-103.345,20.702],"riesgo":19},
{"nombre_colonia":"Jardines De Guadalupe","centro":[-103.405,20.675],"riesgo":89},
{"nombre_colonia":"Jardines De La Barranca","centro":[-103.272,20.718],"riesgo":36},
{"nombre_colonia":"Jardines De La Cruz","centro":[-103.385,20.635],"riesgo":18},
{"nombre_colonia":"Jardines Del Bosque","centro":[-103.385,20.668],"riesgo":88},
{"nombre_colonia":"Jardines De Los Belenes","centro":[-103.345,20.722],"riesgo":54},
{"nombre_colonia":"Jardines De San Francisco","centro":[-103.275,20.662],"riesgo":46},
{"nombre_colonia":"Jardines De San Ignacio","centro":[-103.402,20.662],"riesgo":40},
{"nombre_colonia":"Jardines De San Jose","centro":[-103.385,20.612],"riesgo":95},
{"nombre_colonia":"Jardines De Santa Isabel","centro":[-103.295,20.715],"riesgo":60},
{"nombre_colonia":"Jardines Del Sauz","centro":[-103.398,20.625],"riesgo":25},
{"nombre_colonia":"Jardines Del Sur","centro":[-103.375,20.618],"riesgo":32},
{"nombre_colonia":"Jose Clemente Orozco","centro":[-103.342,20.692],"riesgo":25},
{"nombre_colonia":"Joyas Del Nilo","centro":[-103.285,20.648],"riesgo":46},
{"nombre_colonia":"Juan Manuel","centro":[-103.365,20.682],"riesgo":27},
{"nombre_colonia":"La Aurora","centro":[-103.315,20.662],"riesgo":79},
{"nombre_colonia":"La Campesina","centro":[-103.302,20.668],"riesgo":24},
{"nombre_colonia":"La Cruz","centro":[-103.315,20.692],"riesgo":13},
{"nombre_colonia":"La Esperanza","centro":[-103.308,20.705],"riesgo":56},
{"nombre_colonia":"La Experiencia","centro":[-103.338,20.732],"riesgo":65},
{"nombre_colonia":"La Guadalupana","centro":[-103.335,20.712],"riesgo":79},
{"nombre_colonia":"La Joya","centro":[-103.308,20.728],"riesgo":20},
{"nombre_colonia":"La Joyita","centro":[-103.292,20.685],"riesgo":83},
{"nombre_colonia":"La Loma","centro":[-103.312,20.655],"riesgo":25},
{"nombre_colonia":"La Malinche","centro":[-103.285,20.688],"riesgo":68},
{"nombre_colonia":"La Nogalera","centro":[-103.345,20.628],"riesgo":20},
{"nombre_colonia":"La Normal","centro":[-103.348,20.695],"riesgo":42},
{"nombre_colonia":"La Paz","centro":[-103.328,20.675],"riesgo":39},
{"nombre_colonia":"La Penal","centro":[-103.305,20.665],"riesgo":43},
{"nombre_colonia":"La Perla","centro":[-103.335,20.678],"riesgo":38},
{"nombre_colonia":"La Pila","centro":[-103.315,20.648],"riesgo":25},
{"nombre_colonia":"Lagos De Oriente","centro":[-103.282,20.675],"riesgo":56},
{"nombre_colonia":"Las Conchas","centro":[-103.338,20.665],"riesgo":54},
{"nombre_colonia":"Las Huertas","centro":[-103.285,20.635],"riesgo":93},
{"nombre_colonia":"Las Juntas","centro":[-103.332,20.605],"riesgo":62},
{"nombre_colonia":"Las Teresas","centro":[-103.305,20.695],"riesgo":77},
{"nombre_colonia":"Lazaro Cardenas","centro":[-103.362,20.635],"riesgo":26},
{"nombre_colonia":"Leyes De Reforma","centro":[-103.328,20.645],"riesgo":39},
{"nombre_colonia":"Libertad","centro":[-103.302,20.682],"riesgo":87},
{"nombre_colonia":"Lindavista","centro":[-103.315,20.652],"riesgo":22},
{"nombre_colonia":"Loma Bonita","centro":[-103.402,20.632],"riesgo":41},
{"nombre_colonia":"Loma Linda","centro":[-103.355,20.605],"riesgo":89},
{"nombre_colonia":"Lomas De Atemajac","centro":[-103.355,20.712],"riesgo":63},
{"nombre_colonia":"Lomas De Guevara","centro":[-103.375,20.685],"riesgo":93},
{"nombre_colonia":"Lomas De Independencia","centro":[-103.315,20.712],"riesgo":12},
{"nombre_colonia":"Lomas De La Victoria","centro":[-103.385,20.628],"riesgo":35},
{"nombre_colonia":"Lomas De Oblatos","centro":[-103.275,20.708],"riesgo":42},
{"nombre_colonia":"Lomas De Polanco","centro":[-103.3654,20.6312],"riesgo":92},
{"nombre_colonia":"Lomas De Rio Verde","centro":[-103.278,20.688],"riesgo":14},
{"nombre_colonia":"Lomas De San Eugenio","centro":[-103.268,20.692],"riesgo":45},
{"nombre_colonia":"Lomas De San Pedro","centro":[-103.308,20.648],"riesgo":78},
{"nombre_colonia":"Lomas Del Bosque","centro":[-103.385,20.695],"riesgo":69},
{"nombre_colonia":"Lomas Del Gallo","centro":[-103.265,20.672],"riesgo":48},
{"nombre_colonia":"Lomas Del Laurel I","centro":[-103.255,20.665],"riesgo":68},
{"nombre_colonia":"Lomas Del Laurel Ii","centro":[-103.253,20.668],"riesgo":21},
{"nombre_colonia":"Lomas Del Paradero","centro":[-103.318,20.648],"riesgo":18},
{"nombre_colonia":"Lomas Del Paraiso I","centro":[-103.325,20.728],"riesgo":57},
{"nombre_colonia":"Lomas Del Paraiso Ii","centro":[-103.322,20.732],"riesgo":95},
{"nombre_colonia":"Lomas Del Paraiso Iii","centro":[-103.318,20.735],"riesgo":46},
{"nombre_colonia":"Lomas Del Pedregal","centro":[-103.275,20.715],"riesgo":20},
{"nombre_colonia":"Lomas Del Valle","centro":[-103.405,20.695],"riesgo":82},
{"nombre_colonia":"Lomas Independencia","centro":[-103.318,20.71],"riesgo":47},
{"nombre_colonia":"Lopez De Legaspi","centro":[-103.368,20.635],"riesgo":59},
{"nombre_colonia":"Lopez Portillo","centro":[-103.365,20.618],"riesgo":76},
{"nombre_colonia":"Los Arcos","centro":[-103.382,20.675],"riesgo":17},
{"nombre_colonia":"Los Colorines","centro":[-103.348,20.605],"riesgo":35},
{"nombre_colonia":"Los Portales Tlaquepaque","centro":[-103.315,20.635],"riesgo":69},
{"nombre_colonia":"Magaña","centro":[-103.322,20.655],"riesgo":48},
{"nombre_colonia":"Margarita Maza De Juarez","centro":[-103.335,20.718],"riesgo":76},
{"nombre_colonia":"Medrano","centro":[-103.318,20.662],"riesgo":40},
{"nombre_colonia":"Meridiano","centro":[-103.325,20.625],"riesgo":47},
{"nombre_colonia":"Mexicaltzingo","centro":[-103.348,20.668],"riesgo":65},
{"nombre_colonia":"Mexico","centro":[-103.382,20.682],"riesgo":65},
{"nombre_colonia":"Mezquitan","centro":[-103.352,20.692],"riesgo":82},
{"nombre_colonia":"Mezquitan Country","centro":[-103.355,20.695],"riesgo":40},
{"nombre_colonia":"Miguel Hidalgo","centro":[-103.285,20.655],"riesgo":52},
{"nombre_colonia":"Mirador","centro":[-103.295,20.688],"riesgo":47},
{"nombre_colonia":"Mirador Alamo Industrial","centro":[-103.328,20.615],"riesgo":44},
{"nombre_colonia":"Mirador Del Tesoro","centro":[-103.395,20.602],"riesgo":50},
{"nombre_colonia":"Miraflores","centro":[-103.338,20.695],"riesgo":38},
{"nombre_colonia":"Miravalle","centro":[-103.345,20.612],"riesgo":84},
{"nombre_colonia":"Mision De La Cantera","centro":[-103.272,20.695],"riesgo":46},
{"nombre_colonia":"Mision San Francisco","centro":[-103.272,20.665],"riesgo":53},
{"nombre_colonia":"Modelo","centro":[-103.352,20.668],"riesgo":88},
{"nombre_colonia":"Moderna","centro":[-103.358,20.665],"riesgo":43},
{"nombre_colonia":"Molino Del Salvador","centro":[-103.262,20.675],"riesgo":79},
{"nombre_colonia":"Monraz","centro":[-103.395,20.682],"riesgo":86},
{"nombre_colonia":"Monumental","centro":[-103.335,20.702],"riesgo":83},
{"nombre_colonia":"Morelos","centro":[-103.355,20.658],"riesgo":96},
{"nombre_colonia":"Niños Heroes","centro":[-103.328,20.648],"riesgo":96},
{"nombre_colonia":"Nueva España","centro":[-103.365,20.628],"riesgo":65},
{"nombre_colonia":"Nueva Santa Maria","centro":[-103.338,20.618],"riesgo":65},
{"nombre_colonia":"Nuevo Israel","centro":[-103.255,20.682],"riesgo":83},
{"nombre_colonia":"Obeliscos","centro":[-103.288,20.662],"riesgo":48},
{"nombre_colonia":"Oblatos","centro":[-103.298,20.692],"riesgo":40},
{"nombre_colonia":"Oblatos Pte","centro":[-103.305,20.695],"riesgo":87},
{"nombre_colonia":"Obrera","centro":[-103.362,20.668],"riesgo":69},
{"nombre_colonia":"Observatorio","centro":[-103.325,20.665],"riesgo":66},
{"nombre_colonia":"Olimpica","centro":[-103.315,20.655],"riesgo":83},
{"nombre_colonia":"Osorio Comunal","centro":[-103.272,20.658],"riesgo":80},
{"nombre_colonia":"Panoramica De Huentitan","centro":[-103.312,20.735],"riesgo":64},
{"nombre_colonia":"Parque Industrial El Alamo","centro":[-103.322,20.618],"riesgo":79},
{"nombre_colonia":"Parques De San Pedro","centro":[-103.315,20.622],"riesgo":28},
{"nombre_colonia":"Parques De Tlaquepaque","centro":[-103.318,20.625],"riesgo":71},
{"nombre_colonia":"Paseos Del Nilo I","centro":[-103.288,20.645],"riesgo":13},
{"nombre_colonia":"Plutarco Elias Calles","centro":[-103.305,20.685],"riesgo":22},
{"nombre_colonia":"Polanco","centro":[-103.368,20.635],"riesgo":72},
{"nombre_colonia":"Polanquito Poniente","centro":[-103.362,20.628],"riesgo":96},
{"nombre_colonia":"Popular","centro":[-103.375,20.645],"riesgo":78},
{"nombre_colonia":"Popular Hornos","centro":[-103.372,20.638],"riesgo":20},
{"nombre_colonia":"POPULAR No 9","centro":[-103.375,20.642],"riesgo":64},
{"nombre_colonia":"Postes Cuates","centro":[-103.322,20.698],"riesgo":19},
{"nombre_colonia":"Progreso","centro":[-103.308,20.672],"riesgo":16},
{"nombre_colonia":"Quinta Velarde","centro":[-103.332,20.658],"riesgo":63},
{"nombre_colonia":"Rancho Blanco","centro":[-103.338,20.642],"riesgo":90},
{"nombre_colonia":"Rancho Nuevo","centro":[-103.335,20.725],"riesgo":37},
{"nombre_colonia":"Real","centro":[-103.308,20.655],"riesgo":62},
{"nombre_colonia":"Reforma","centro":[-103.312,20.658],"riesgo":21},
{"nombre_colonia":"Residencial De La Barranca","centro":[-103.278,20.722],"riesgo":88},
{"nombre_colonia":"Revolucion","centro":[-103.305,20.652],"riesgo":82},
{"nombre_colonia":"Revolucionaria","centro":[-103.298,20.655],"riesgo":30},
{"nombre_colonia":"Ricardo Flores Magon","centro":[-103.288,20.675],"riesgo":77},
{"nombre_colonia":"Rincon De La Agua Azul","centro":[-103.342,20.655],"riesgo":63},
{"nombre_colonia":"Rio Verde","centro":[-103.272,20.685],"riesgo":60},
{"nombre_colonia":"Roxy Autocinema","centro":[-103.338,20.708],"riesgo":16},
{"nombre_colonia":"San Andres","centro":[-103.292,20.665],"riesgo":49},
{"nombre_colonia":"San Antonio","centro":[-103.328,20.658],"riesgo":30},
{"nombre_colonia":"San Bernardo","centro":[-103.352,20.715],"riesgo":63},
{"nombre_colonia":"San Carlos","centro":[-103.332,20.645],"riesgo":95},
{"nombre_colonia":"San Elias","centro":[-103.272,20.678],"riesgo":20},
{"nombre_colonia":"San Eugenio","centro":[-103.265,20.688],"riesgo":60},
{"nombre_colonia":"San Francisco","centro":[-103.275,20.655],"riesgo":74},
{"nombre_colonia":"San Isidro","centro":[-103.328,20.718],"riesgo":57},
{"nombre_colonia":"San Isidro Oblatos","centro":[-103.272,20.705],"riesgo":25},
{"nombre_colonia":"San Jose","centro":[-103.295,20.692],"riesgo":72},
{"nombre_colonia":"San Jose Rio Verde","centro":[-103.268,20.685],"riesgo":75},
{"nombre_colonia":"San Juan","centro":[-103.292,20.678],"riesgo":44},
{"nombre_colonia":"San Juan Bosco","centro":[-103.315,20.675],"riesgo":16},
{"nombre_colonia":"San Juan De Dios","centro":[-103.338,20.675],"riesgo":76},
{"nombre_colonia":"San Juan De Dios Ii","centro":[-103.335,20.672],"riesgo":22},
{"nombre_colonia":"San Marcos","centro":[-103.318,20.695],"riesgo":65},
{"nombre_colonia":"San Martin","centro":[-103.282,20.685],"riesgo":56},
{"nombre_colonia":"San Miguel De Huentitan","centro":[-103.295,20.725],"riesgo":61},
{"nombre_colonia":"San Miguel De Mezquitan","centro":[-103.355,20.698],"riesgo":46},
{"nombre_colonia":"San Pantaleon","centro":[-103.275,20.675],"riesgo":65},
{"nombre_colonia":"San Rafael","centro":[-103.302,20.648],"riesgo":17},
{"nombre_colonia":"San Vicente","centro":[-103.315,20.702],"riesgo":36},
{"nombre_colonia":"Santa Cecilia","centro":[-103.265,20.705],"riesgo":26},
{"nombre_colonia":"Santa Eduwiges","centro":[-103.385,20.645],"riesgo":38},
{"nombre_colonia":"Santa Elena Alcalde","centro":[-103.348,20.712],"riesgo":20},
{"nombre_colonia":"Santa Elena De La Cruz","centro":[-103.338,20.718],"riesgo":53},
{"nombre_colonia":"Santa Elena Estadio","centro":[-103.328,20.708],"riesgo":70},
{"nombre_colonia":"Santa Fe","centro":[-103.332,20.678],"riesgo":81},
{"nombre_colonia":"Santa Isabel","centro":[-103.288,20.715],"riesgo":26},
{"nombre_colonia":"Santa Ma De Silo","centro":[-103.268,20.682],"riesgo":95},
{"nombre_colonia":"Santa Maria","centro":[-103.328,20.695],"riesgo":35},
{"nombre_colonia":"Santa Monica","centro":[-103.348,20.682],"riesgo":79},
{"nombre_colonia":"Santa Rita","centro":[-103.398,20.658],"riesgo":57},
{"nombre_colonia":"Santa Rosa","centro":[-103.292,20.692],"riesgo":22},
{"nombre_colonia":"Santos Degollado","centro":[-103.335,20.645],"riesgo":55},
{"nombre_colonia":"Sutaj","centro":[-103.308,20.642],"riesgo":62},
{"nombre_colonia":"Talpita","centro":[-103.308,20.688],"riesgo":60},
{"nombre_colonia":"Tetlan","centro":[-103.278,20.662],"riesgo":41},
{"nombre_colonia":"Tetlan Ii","centro":[-103.275,20.658],"riesgo":71},
{"nombre_colonia":"Tiro A Rio Verde","centro":[-103.265,20.682],"riesgo":37},
{"nombre_colonia":"Torres España","centro":[-103.298,20.635],"riesgo":60},
{"nombre_colonia":"Vicente Guerrero","centro":[-103.275,20.685],"riesgo":39},
{"nombre_colonia":"Victor Hugo","centro":[-103.345,20.715],"riesgo":91},
{"nombre_colonia":"Villa Guerrero","centro":[-103.375,20.622],"riesgo":65},
{"nombre_colonia":"Villa Hermosa","centro":[-103.292,20.652],"riesgo":49},
{"nombre_colonia":"Villas Alcalde","centro":[-103.348,20.715],"riesgo":35},
{"nombre_colonia":"Villas De Guadalupe","centro":[-103.332,20.722],"riesgo":63},
{"nombre_colonia":"Villas De Oriente I","centro":[-103.255,20.655],"riesgo":41},
{"nombre_colonia":"Villas De San Juan","centro":[-103.298,20.718],"riesgo":14},
{"nombre_colonia":"Villas Del Oriente Ii","centro":[-103.252,20.652],"riesgo":24},
{"nombre_colonia":"Villaseñor (Santa Teresita)","centro":[-103.358,20.685],"riesgo":30},
{"nombre_colonia":"Vistas Del Nilo","centro":[-103.295,20.642],"riesgo":46},
{"nombre_colonia":"Zalatitan Centro","centro":[-103.2678,20.6541],"riesgo":68},
{"nombre_colonia":"Zona Centro","centro":[-103.346,20.676],"riesgo":35},
{"nombre_colonia":"Zona Industrial","centro":[-103.355,20.642],"riesgo":47}
]